{
  "monster": [
{"id":0,  "name":"Dummy", "name_fr": "Dummy"},
{"id":1,  "name":"GIM52A", "name_fr": "ExoSkelet"},
{"id":2,  "name":"Blobra", "name_fr": "Incube"},
{"id":3,  "name":"Thrustaevis", "name_fr": "Malaku"},
{"id":4,  "name":"Geezard", "name_fr": "Bogomile"},
{"id":5,  "name":"Belhelmel", "name_fr": "Koatl"},
{"id":6,  "name":"Glacial Eye", "name_fr": "Xylopode"},
{"id":7,  "name":"SAM08G", "name_fr": "Barbarian"},
{"id":8,  "name":"GIM47N", "name_fr": "Pikasso"},
{"id":9,  "name":"Mesmerize", "name_fr": "Licorne"},
{"id":10, "name":"Buel", "name_fr": "Schizoïd"},
{"id":11, "name":"Sphinxaur", "name_fr": "Brahman"},
{"id":12, "name":"Sphinxara", "name_fr": "Shiva"},
{"id":13, "name":"Snow Lion", "name_fr": "Satyrux"},
{"id":14, "name":"Anacondaur", "name_fr": "Arconada"},
{"id":15, "name":"Grat", "name_fr": "Orchida"},
{"id":16, "name":"Cockatrice", "name_fr": "Gallus"},
{"id":17, "name":"Caterchipillar", "name_fr": "Larva"},
{"id":18, "name":"Red Bat", "name_fr": "Nocturnus"},
{"id":19, "name":"Blitz", "name_fr": "Tikal"},
{"id":20, "name":"Fastitocalon", "name_fr": "Diodon"},
{"id":21, "name":"Fastitocalon", "name_fr": "Phantom"},
{"id":22, "name":"Gesper", "name_fr": "Elastos"},
{"id":23, "name":"Creeps", "name_fr": "Formicide"},
{"id":24, "name":"Hexadragon", "name_fr": "Polyphage"},
{"id":25, "name":"Blood Soul", "name_fr": "Carnidea"},
{"id":26, "name":"Elastoid", "name_fr": "Protesis"},
{"id":27, "name":"Armadodo", "name_fr": "Scavenger"},
{"id":28, "name":"Bite Bug", "name_fr": "Elmidea"},
{"id":29, "name":"Jelleye", "name_fr": "Héra"},
{"id":30, "name":"Tri-Point", "name_fr": "Acron"},
{"id":31, "name":"Turtapod", "name_fr": "Eiffel"},
{"id":32, "name":"Wendigo", "name_fr": "Wendigo"},
{"id":33, "name":"Gayla", "name_fr": "Aphide"},
{"id":34, "name":"Gerogero", "name_fr": "Ecorché"},
{"id":35, "name":"Death Claw", "name_fr": "Berserker"},
{"id":36, "name":"Tri-Face", "name_fr": "Adéphage"},
{"id":37, "name":"Grand Mantis", "name_fr": "Selek"},
{"id":38, "name":"Krysta", "name_fr": "Krystal"},
{"id":39, "name":"Lefty", "name_fr": "Gangrène"},
{"id":40, "name":"Righty", "name_fr": "Fatima"},
{"id":41, "name":"Blue Dragon", "name_fr": "Moloch"},
{"id":42, "name":"Forbidden", "name_fr": "Weevil"},
{"id":43, "name":"Bomb", "name_fr": "Succube"},
{"id":44, "name":"Abyss Worm", "name_fr": "Célébis"},
{"id":45, "name":"Ochu", "name_fr": "Trogiidae"},
{"id":46, "name":"Adamantoise", "name_fr": "Ao"},
{"id":47, "name":"Chimera", "name_fr": "Chimaira"},
{"id":48, "name":"Malboro", "name_fr": "Xylomid"},
{"id":49, "name":"Iron Giant", "name_fr": "Ekarissor"},
{"id":50, "name":"Behemoth", "name_fr": "Kanibal"},
{"id":51, "name":"T-Rexaur", "name_fr": "T-Rex"},
{"id":52, "name":"Ruby Dragon", "name_fr": "Griffon"},
{"id":53, "name":"Grendel", "name_fr": "Feng"},
{"id":54, "name":"Vysage", "name_fr": "Cariatide"},
{"id":55, "name":"Cactuar", "name_fr": "Pampa"},
{"id":56, "name":"Tonberry", "name_fr": "Tomberry"},
{"id":57, "name":"Torama", "name_fr": "Marsupial"},
{"id":58, "name":"Funguar", "name_fr": "Fungus"},
{"id":59, "name":"Imp", "name_fr": "Draconus"},
{"id":60, "name":"PuPu", "name_fr": "Koyo K"},
{"id":61, "name":"Ifrit", "name_fr": "Ifrit"},
{"id":62, "name":"Minotaur", "name_fr": "Taurux"},
{"id":63, "name":"Sacred", "name_fr": "Tauros"},
{"id":64, "name":"Base Leader", "name_fr": "Commandeur"},
{"id":65, "name":"Cerberus", "name_fr": "Cerbères"},
{"id":66, "name":"Diablos", "name_fr": "Nosferatu"},
{"id":67, "name":"Bahamut", "name_fr": "Bahamut"},
{"id":68, "name":"NORG Pod", "name_fr": "Odyssey"},
{"id":69, "name":"Garden Faculty", "name_fr": "Templier"},
{"id":70, "name":"Odin", "name_fr": "Odin"},
{"id":71, "name":"G-Soldier", "name_fr": "Galbadien"},
{"id":72, "name":"Elite Soldier", "name_fr": "Elite-T"},
{"id":73, "name":"Wedge", "name_fr": "Wedge"},
{"id":74, "name":"Biggs", "name_fr": "Biggs"},
{"id":75, "name":"Fake President", "name_fr": "Doublure"},
{"id":76, "name":"Guard", "name_fr": "Trooper"},
{"id":77, "name":"NORG", "name_fr": "Norg"},
{"id":78, "name":"Esthar Soldier", "name_fr": "S-Borg"},
{"id":79, "name":"Esthar Soldier", "name_fr": "T-Borg"},
{"id":80, "name":"Right Orb", "name_fr": "Tupolev"},
{"id":81, "name":"Left Orb", "name_fr": "Spootnik"},
{"id":82, "name":"Gunblade", "name_fr": "Gunblade"},
{"id":83, "name":"Tonberry King", "name_fr": "Tomberry Sr"},
{"id":84, "name":"Jumbo Cactuar", "name_fr": "Pampa Senior"},
{"id":85, "name":"Seifer", "name_fr": "Seifer"},
{"id":86, "name":"Seifer", "name_fr": "Seifer"},
{"id":87, "name":"Seifer", "name_fr": "Seifer"},
{"id":88, "name":"Edea", "name_fr": "Edea"},
{"id":89, "name":"Propagator", "name_fr": "Alienator"},
{"id":90, "name":"Ultima Weapon", "name_fr": "Monarch"},
{"id":91, "name":"Elvoret", "name_fr": "Sulfura"},
{"id":92, "name":"X-ATM092", "name_fr": "Goliath"},
{"id":93, "name":"Iguion", "name_fr": "Iguanor"},
{"id":94, "name":"Gargantua", "name_fr": "Agamemnon"},
{"id":95, "name":"Granaldo", "name_fr": "Lygus"},
{"id":96, "name":"Raldo", "name_fr": "Cujo"},
{"id":97, "name":"Propagator", "name_fr": "Alienator"},
{"id":98, "name":"Propagator", "name_fr": "Alienator"},
{"id":99, "name":"Oilboyle", "name_fr": "Cyanide"},
{"id":100,"name":"Edea", "name_fr": "Edea"},
{"id":101,"name":"BGH251F2", "name_fr": "Omniborg"},
{"id":102,"name":"BGH251F2", "name_fr": "Omniborg"},
{"id":103,"name":"Abadon", "name_fr": "Hornet"},
{"id":104,"name":"Abadon", "name_fr": "Hornet"},
{"id":105,"name":"Mobile Type 8", "name_fr": "Anakronox"},
{"id":106,"name":"Left Probe", "name_fr": "A-G Pod"},
{"id":107,"name":"Right Probe", "name_fr": "A-D Pod"},
{"id":108,"name":"Paratrooper", "name_fr": "ParaBorg"},
{"id":109,"name":"Trauma", "name_fr": "Flotix"},
{"id":110,"name":"Droma", "name_fr": "Bibendum"},
{"id":111,"name":"Propagator", "name_fr": "Alienator"},
{"id":112,"name":"Adel", "name_fr": "Adel"},
{"id":113,"name":"{Rinoa}", "name_fr": "{Rinoa}"},
{"id":114,"name":"Omega Weapon", "name_fr": "Minotaure"},
{"id":115,"name":"“Sorceress”", "name_fr": "Nécromancienne"},
{"id":116,"name":"“Sorceress”", "name_fr": "Nécromancienne"},
{"id":117,"name":"“Sorceress”", "name_fr": "Nécromancienne"},
{"id":118,"name":"UFO?", "name_fr": "UFO"},
{"id":119,"name":"Fujin", "name_fr": "Fujin"},
{"id":120,"name":"Raijin", "name_fr": "Raijin"},
{"id":121,"name":"Ultimecia", "name_fr": "Ultimecia"},
{"id":122,"name":"{Griever}", "name_fr": "{Griever}"},
{"id":123,"name":"", "name_fr": ""},
{"id":124,"name":"Ultimecia", "name_fr": "Ultimecia"},
{"id":125,"name":"Helix", "name_fr": "Hélix"},
{"id":126,"name":"Ultimecia", "name_fr": "Ultimecia"},
{"id":127,"name":"127garbage", "name_fr": "127Garbage"},
{"id":128,"name":"Seifer", "name_fr": "Seifer"},
{"id":129,"name":"Slapper", "name_fr": "Jason"},
{"id":130,"name":"Red Giant", "name_fr": "Attila"},
{"id":131,"name":"Elnoyle", "name_fr": "Sulfor"},
{"id":132,"name":"Tiamat", "name_fr": "Acarnan"},
{"id":133,"name":"Catoblepas", "name_fr": "Fabryce"},
{"id":134,"name":"Wedge", "name_fr": "Wedge"},
{"id":135,"name":"Biggs", "name_fr": "Biggs"},
{"id":136,"name":"Fujin", "name_fr": "Fujin"},
{"id":137,"name":"Raijin", "name_fr": "Raijin"},
{"id":138,"name":"UFO?", "name_fr": "UFO"},
{"id":139,"name":"UFO?", "name_fr": "UFO"},
{"id":140,"name":"UFO?", "name_fr": "UFO"},
{"id":141,"name":"UFO?", "name_fr": "UFO"},
{"id":142,"name":"Gunblade", "name_fr": "Gunblade"},
{"id":143,"name":"Base Soldier", "name_fr": "Soldat"}
]
}